?xml version="1.0" encoding="UTF-8" standalone="yes"?>

<item>
<title>Pistoleros Famosos </title>        
<urlsolve>https://www.youtube.com/watch?v=N_JVGNMg490</urlsolve>
<thumbnail>https://www.art-books.com/pictures/55-2340.jpg?v=1193776732</thumbnail>
<fanart>http://4.bp.blogspot.com/-XgV0mOz0HCU/TgyuQ-0TJVI/AAAAAAAAA4M/0mE62HuOF3s/s1600/Picture+182.jpg</fanart>
</item>
<item>
<title>Emilio Varela vs Camelia la Texana </title>        
<urlsolve>https://www.youtube.com/watch?v=qPij78dd_QE</urlsolve>
<thumbnail>https://i.ytimg.com/vi/Pu7J2S-pnDM/hqdefault.jpg</thumbnail>
<fanart>http://cps-static.rovicorp.com/1/adg/covers/drt900/t972/t97209ub35e.jpg?partner=allrovi.com</fanart>
</item>